{"1":{"1":[{"w":"Παῦλος","i":"Paul"},{"w":"ἀπόστολος","i":"an apostle"},{"w":"Χριστοῦ","i":"of Christ"},{"w":"Ἰησοῦ","i":"Jesus"},{"w":"διὰ","i":"by"},{"w":"θελήματος","i":"[the] will"},{"w":"Θεοῦ","i":"of God,"},{"w":"καὶ","i":"and"},{"w":"Τιμόθεος","i":"Timothy"},{"w":"ὁ","i":"the"},{"w":"ἀδελφὸς","i":"brother,"}],"2":[{"w":"Τοῖς","i":"To the"},{"w":"ἐν","i":"in"},{"w":"Κολοσσαῖς","i":"Colossae"},{"w":"ἁγίοις","i":"saints"},{"w":"καὶ","i":"and"},{"w":"πιστοῖς","i":"faithful"},{"w":"ἀδελφοῖς","i":"brothers"},{"w":"ἐν","i":"in"},{"w":"Χριστῷ","i":"Christ:"},{"w":"Χάρις","i":"Grace"},{"w":"ὑμῖν","i":"to you"},{"w":"καὶ","i":"and"},{"w":"εἰρήνη","i":"peace"},{"w":"ἀπὸ","i":"from"},{"w":"Θεοῦ","i":"God"},{"w":"Πατρὸς","i":"[the] Father"},{"w":"ἡμῶν","i":"of us."}],"3":[{"w":"Εὐχαριστοῦμεν","i":"We give thanks"},{"w":"τῷ","i":"to the"},{"w":"Θεῷ","i":"God"},{"w":"Πατρὶ","i":"[and] Father"},{"w":"τοῦ","i":"of the"},{"w":"Κυρίου","i":"Lord"},{"w":"ἡμῶν","i":"of us"},{"w":"Ἰησοῦ","i":"Jesus"},{"w":"Χριστοῦ","i":"Christ,"},{"w":"πάντοτε","i":"continually"},{"w":"περὶ","i":"for"},{"w":"ὑμῶν","i":"you"},{"w":"προσευχόμενοι","i":"praying,"}],"4":[{"w":"ἀκούσαντες","i":"having heard of"},{"w":"τὴν","i":"the"},{"w":"πίστιν","i":"faith"},{"w":"ὑμῶν","i":"of you"},{"w":"ἐν","i":"in"},{"w":"Χριστῷ","i":"Christ"},{"w":"Ἰησοῦ","i":"Jesus"},{"w":"καὶ","i":"and"},{"w":"τὴν","i":"the"},{"w":"ἀγάπην","i":"love"},{"w":"ἣν","i":"that"},{"w":"ἔχετε","i":"you have"},{"w":"εἰς","i":"toward"},{"w":"πάντας","i":"all"},{"w":"τοὺς","i":"the"},{"w":"ἁγίους","i":"saints,"}],"5":[{"w":"διὰ","i":"because of"},{"w":"τὴν","i":"the"},{"w":"ἐλπίδα","i":"hope"},{"w":"τὴν","i":"-"},{"w":"ἀποκειμένην","i":"being laid up"},{"w":"ὑμῖν","i":"for you"},{"w":"ἐν","i":"in"},{"w":"τοῖς","i":"the"},{"w":"οὐρανοῖς","i":"heavens,"},{"w":"ἣν","i":"which"},{"w":"προηκούσατε","i":"you heard of before"},{"w":"ἐν","i":"in"},{"w":"τῷ","i":"the"},{"w":"λόγῳ","i":"word"},{"w":"τῆς","i":"of"},{"w":"ἀληθείας","i":"truth,"},{"w":"τοῦ","i":"the"},{"w":"εὐαγγελίου","i":"gospel,"}],"6":[{"w":"τοῦ","i":"the [one]"},{"w":"παρόντος","i":"being present"},{"w":"εἰς","i":"unto"},{"w":"ὑμᾶς","i":"you,"},{"w":"καθὼς","i":"just as"},{"w":"καὶ","i":"also"},{"w":"ἐν","i":"in"},{"w":"παντὶ","i":"all"},{"w":"τῷ","i":"the"},{"w":"κόσμῳ","i":"world"},{"w":"ἐστὶν","i":"it is"},{"w":"καρποφορούμενον","i":"bearing fruit"},{"w":"καὶ","i":"and"},{"w":"αὐξανόμενον","i":"increasing,"},{"w":"καθὼς","i":"just as"},{"w":"καὶ","i":"also"},{"w":"ἐν","i":"among"},{"w":"ὑμῖν","i":"you,"},{"w":"ἀφ᾽","i":"from"},{"w":"ἧς","i":"the"},{"w":"ἡμέρας","i":"day"},{"w":"ἠκούσατε","i":"you heard"},{"w":"καὶ","i":"and"},{"w":"ἐπέγνωτε","i":"knew"},{"w":"τὴν","i":"the"},{"w":"χάριν","i":"grace"},{"w":"τοῦ","i":"-"},{"w":"Θεοῦ","i":"of God"},{"w":"ἐν","i":"in"},{"w":"ἀληθείᾳ","i":"truth,"}],"7":[{"w":"καθὼς","i":"just as"},{"w":"ἐμάθετε","i":"you learned"},{"w":"ἀπὸ","i":"from"},{"w":"Ἐπαφρᾶ","i":"Epaphras,"},{"w":"τοῦ","i":"the"},{"w":"ἀγαπητοῦ","i":"beloved"},{"w":"συνδούλου","i":"fellow bond-servant"},{"w":"ἡμῶν","i":"of us,"},{"w":"ὅς","i":"who"},{"w":"ἐστιν","i":"is"},{"w":"πιστὸς","i":"faithful"},{"w":"ὑπὲρ","i":"on behalf of"},{"w":"ἡμῶν","i":"us,"},{"w":"διάκονος","i":"a servant"},{"w":"τοῦ","i":"-"},{"w":"Χριστοῦ","i":"of Christ,"}],"8":[{"w":"ὁ","i":"the [one]"},{"w":"καὶ","i":"also"},{"w":"δηλώσας","i":"having made known"},{"w":"ἡμῖν","i":"to us"},{"w":"τὴν","i":"-"},{"w":"ὑμῶν","i":"your"},{"w":"ἀγάπην","i":"love"},{"w":"ἐν","i":"in"},{"w":"Πνεύματι","i":"[the] Spirit."}],"9":[{"w":"Διὰ","i":"Because of"},{"w":"τοῦτο","i":"this"},{"w":"καὶ","i":"also"},{"w":"ἡμεῖς","i":"we"},{"w":"ἀφ᾽","i":"from"},{"w":"ἧς","i":"the"},{"w":"ἡμέρας","i":"day"},{"w":"ἠκούσαμεν","i":"we heard,"},{"w":"οὐ","i":"not"},{"w":"παυόμεθα","i":"cease"},{"w":"ὑπὲρ","i":"for"},{"w":"ὑμῶν","i":"you"},{"w":"προσευχόμενοι","i":"praying"},{"w":"καὶ","i":"and"},{"w":"αἰτούμενοι","i":"asking"},{"w":"ἵνα","i":"that"},{"w":"πληρωθῆτε","i":"you may be filled with"},{"w":"τὴν","i":"the"},{"w":"ἐπίγνωσιν","i":"knowledge"},{"w":"τοῦ","i":"of the"},{"w":"θελήματος","i":"will"},{"w":"αὐτοῦ","i":"of Him"},{"w":"ἐν","i":"in"},{"w":"πάσῃ","i":"all"},{"w":"σοφίᾳ","i":"wisdom"},{"w":"καὶ","i":"and"},{"w":"συνέσει","i":"understanding"},{"w":"πνευματικῇ","i":"spiritual,"}],"10":[{"w":"περιπατῆσαι","i":"to walk"},{"w":"ἀξίως","i":"worthily"},{"w":"τοῦ","i":"of the"},{"w":"Κυρίου","i":"Lord:"},{"w":"εἰς","i":"in"},{"w":"πᾶσαν","i":"all"},{"w":"ἀρεσκείαν","i":"pleasing,"},{"w":"ἐν","i":"in"},{"w":"παντὶ","i":"every"},{"w":"ἔργῳ","i":"work"},{"w":"ἀγαθῷ","i":"good,"},{"w":"καρποφοροῦντες","i":"bringing forth fruit"},{"w":"καὶ","i":"and"},{"w":"αὐξανόμενοι","i":"growing"},{"w":"τῇ","i":"in the"},{"w":"ἐπιγνώσει","i":"knowledge"},{"w":"τοῦ","i":"-"},{"w":"Θεοῦ","i":"of God,"}],"11":[{"w":"ἐν","i":"with"},{"w":"πάσῃ","i":"all"},{"w":"δυνάμει","i":"power"},{"w":"δυναμούμενοι","i":"being strengthened"},{"w":"κατὰ","i":"according to"},{"w":"τὸ","i":"the"},{"w":"κράτος","i":"might"},{"w":"τῆς","i":"-"},{"w":"δόξης","i":"glorious"},{"w":"αὐτοῦ","i":"of Him"},{"w":"εἰς","i":"unto"},{"w":"πᾶσαν","i":"all"},{"w":"ὑπομονὴν","i":"endurance"},{"w":"καὶ","i":"and"},{"w":"μακροθυμίαν","i":"patience"},{"w":"μετὰ","i":"with"},{"w":"χαρᾶς","i":"joy,"}],"12":[{"w":"εὐχαριστοῦντες","i":"giving thanks"},{"w":"τῷ","i":"to the"},{"w":"Πατρὶ","i":"Father,"},{"w":"τῷ","i":"the [One]"},{"w":"ἱκανώσαντι","i":"having qualified"},{"w":"ὑμᾶς","i":"you"},{"w":"εἰς","i":"for"},{"w":"τὴν","i":"the"},{"w":"μερίδα","i":"share"},{"w":"τοῦ","i":"of the"},{"w":"κλήρου","i":"inheritance"},{"w":"τῶν","i":"of the"},{"w":"ἁγίων","i":"saints"},{"w":"ἐν","i":"in"},{"w":"τῷ","i":"the"},{"w":"φωτί","i":"light,"}],"13":[{"w":"ὃς","i":"who"},{"w":"ἐρρύσατο","i":"has delivered"},{"w":"ἡμᾶς","i":"us"},{"w":"ἐκ","i":"from"},{"w":"τῆς","i":"the"},{"w":"ἐξουσίας","i":"dominion"},{"w":"τοῦ","i":"-"},{"w":"σκότους","i":"of darkness"},{"w":"καὶ","i":"and"},{"w":"μετέστησεν","i":"transferred [us]"},{"w":"εἰς","i":"into"},{"w":"τὴν","i":"the"},{"w":"βασιλείαν","i":"kingdom"},{"w":"τοῦ","i":"of the"},{"w":"Υἱοῦ","i":"Son"},{"w":"τῆς","i":"-"},{"w":"ἀγάπης","i":"beloved"},{"w":"αὐτοῦ","i":"of Him,"}],"14":[{"w":"ἐν","i":"in"},{"w":"ᾧ","i":"whom"},{"w":"ἔχομεν","i":"we have"},{"w":"τὴν","i":"-"},{"w":"ἀπολύτρωσιν","i":"redemption,"},{"w":"τὴν","i":"the"},{"w":"ἄφεσιν","i":"forgiveness"},{"w":"τῶν","i":"-"},{"w":"ἁμαρτιῶν","i":"of sins."}],"15":[{"w":"Ὅς","i":"[He]"},{"w":"ἐστιν","i":"is"},{"w":"εἰκὼν","i":"[the] image"},{"w":"τοῦ","i":"of the"},{"w":"Θεοῦ","i":"God"},{"w":"τοῦ","i":"-"},{"w":"ἀοράτου","i":"invisible,"},{"w":"πρωτότοκος","i":"[the] firstborn"},{"w":"πάσης","i":"over all"},{"w":"κτίσεως","i":"creation,"}],"16":[{"w":"ὅτι","i":"because"},{"w":"ἐν","i":"in"},{"w":"αὐτῷ","i":"Him"},{"w":"ἐκτίσθη","i":"were created"},{"w":"τὰ","i":"-"},{"w":"πάντα","i":"all things"},{"w":"ἐν","i":"in"},{"w":"τοῖς","i":"the"},{"w":"οὐρανοῖς","i":"heavens"},{"w":"καὶ","i":"and"},{"w":"ἐπὶ","i":"upon"},{"w":"τῆς","i":"the"},{"w":"γῆς","i":"earth,"},{"w":"τὰ","i":"the"},{"w":"ὁρατὰ","i":"visible"},{"w":"καὶ","i":"and"},{"w":"τὰ","i":"the"},{"w":"ἀόρατα","i":"invisible,"},{"w":"εἴτε","i":"whether"},{"w":"θρόνοι","i":"thrones"},{"w":"εἴτε","i":"or"},{"w":"κυριότητες","i":"dominions"},{"w":"εἴτε","i":"or"},{"w":"ἀρχαὶ","i":"rulers"},{"w":"εἴτε","i":"or"},{"w":"ἐξουσίαι","i":"authorities;"},{"w":"τὰ","i":"-"},{"w":"πάντα","i":"all things"},{"w":"δι᾽","i":"through"},{"w":"αὐτοῦ","i":"Him"},{"w":"καὶ","i":"and"},{"w":"εἰς","i":"unto"},{"w":"αὐτὸν","i":"Him"},{"w":"ἔκτισται","i":"have been created."}],"17":[{"w":"Καὶ","i":"And"},{"w":"αὐτός","i":"He"},{"w":"ἐστιν","i":"is"},{"w":"πρὸ","i":"before"},{"w":"πάντων","i":"all things,"},{"w":"καὶ","i":"and"},{"w":"τὰ","i":"-"},{"w":"πάντα","i":"all things"},{"w":"ἐν","i":"in"},{"w":"αὐτῷ","i":"Him"},{"w":"συνέστηκεν","i":"hold together."}],"18":[{"w":"καὶ","i":"And"},{"w":"αὐτός","i":"He"},{"w":"ἐστιν","i":"is"},{"w":"ἡ","i":"the"},{"w":"κεφαλὴ","i":"head"},{"w":"τοῦ","i":"of the"},{"w":"σώματος","i":"body,"},{"w":"τῆς","i":"the"},{"w":"ἐκκλησίας","i":"church,"},{"w":"ὅς","i":"who"},{"w":"ἐστιν","i":"is"},{"w":"ἀρχή","i":"[the] beginning,"},{"w":"πρωτότοκος","i":"firstborn"},{"w":"ἐκ","i":"out from"},{"w":"τῶν","i":"the"},{"w":"νεκρῶν","i":"dead,"},{"w":"ἵνα","i":"so that"},{"w":"γένηται","i":"might be"},{"w":"ἐν","i":"in"},{"w":"πᾶσιν","i":"all things"},{"w":"αὐτὸς","i":"He"},{"w":"πρωτεύων","i":"holding preeminence,"}],"19":[{"w":"ὅτι","i":"because"},{"w":"ἐν","i":"in"},{"w":"αὐτῷ","i":"Him"},{"w":"εὐδόκησεν","i":"was pleased"},{"w":"πᾶν","i":"all"},{"w":"τὸ","i":"the"},{"w":"πλήρωμα","i":"fullness"},{"w":"κατοικῆσαι","i":"to dwell,"}],"20":[{"w":"καὶ","i":"and"},{"w":"δι᾽","i":"by"},{"w":"αὐτοῦ","i":"Him"},{"w":"ἀποκαταλλάξαι","i":"to reconcile"},{"w":"τὰ","i":"-"},{"w":"πάντα","i":"all things"},{"w":"εἰς","i":"to"},{"w":"αὐτόν","i":"Himself,"},{"w":"εἰρηνοποιήσας","i":"having made peace"},{"w":"διὰ","i":"by"},{"w":"τοῦ","i":"the"},{"w":"αἵματος","i":"blood"},{"w":"τοῦ","i":"of the"},{"w":"σταυροῦ","i":"cross"},{"w":"αὐτοῦ","i":"of Him,"},{"w":"δι᾽","i":"through"},{"w":"αὐτοῦ","i":"Him,"},{"w":"εἴτε","i":"whether"},{"w":"τὰ","i":"the things"},{"w":"ἐπὶ","i":"on"},{"w":"τῆς","i":"the"},{"w":"γῆς","i":"earth,"},{"w":"εἴτε","i":"or"},{"w":"τὰ","i":"the things"},{"w":"ἐν","i":"in"},{"w":"τοῖς","i":"the"},{"w":"οὐρανοῖς","i":"heavens."}],"21":[{"w":"Καὶ","i":"And"},{"w":"ὑμᾶς","i":"you,"},{"w":"ποτε","i":"once"},{"w":"ὄντας","i":"being"},{"w":"ἀπηλλοτριωμένους","i":"alienated"},{"w":"καὶ","i":"and"},{"w":"ἐχθροὺς","i":"hostile"},{"w":"τῇ","i":"-"},{"w":"διανοίᾳ","i":"in mind"},{"w":"ἐν","i":"in"},{"w":"τοῖς","i":"the"},{"w":"ἔργοις","i":"deeds"},{"w":"τοῖς","i":"-"},{"w":"πονηροῖς","i":"evil,"}],"22":[{"w":"νυνὶ","i":"now"},{"w":"δὲ","i":"however"},{"w":"ἀποκατήλλαξεν","i":"He has reconciled [You]"},{"w":"ἐν","i":"in"},{"w":"τῷ","i":"the"},{"w":"σώματι","i":"body"},{"w":"τῆς","i":"of the"},{"w":"σαρκὸς","i":"flesh"},{"w":"αὐτοῦ","i":"of Him"},{"w":"διὰ","i":"through"},{"w":"τοῦ","i":"-"},{"w":"θανάτου","i":"death,"},{"w":"παραστῆσαι","i":"to present"},{"w":"ὑμᾶς","i":"you"},{"w":"ἁγίους","i":"holy"},{"w":"καὶ","i":"and"},{"w":"ἀμώμους","i":"unblemished"},{"w":"καὶ","i":"and"},{"w":"ἀνεγκλήτους","i":"blameless"},{"w":"κατενώπιον","i":"before"},{"w":"αὐτοῦ","i":"Him,"}],"23":[{"w":"εἴ","i":"if"},{"w":"γε","i":"indeed"},{"w":"ἐπιμένετε","i":"you continue"},{"w":"τῇ","i":"-"},{"w":"πίστει","i":"in the faith,"},{"w":"τεθεμελιωμένοι","i":"established"},{"w":"καὶ","i":"and"},{"w":"ἑδραῖοι","i":"firm,"},{"w":"καὶ","i":"and"},{"w":"μὴ","i":"not"},{"w":"μετακινούμενοι","i":"being moved away"},{"w":"ἀπὸ","i":"from"},{"w":"τῆς","i":"the"},{"w":"ἐλπίδος","i":"hope"},{"w":"τοῦ","i":"of the"},{"w":"εὐαγγελίου","i":"gospel"},{"w":"οὗ","i":"that"},{"w":"ἠκούσατε","i":"you have heard,"},{"w":"τοῦ","i":"-"},{"w":"κηρυχθέντος","i":"having been proclaimed"},{"w":"ἐν","i":"in"},{"w":"πάσῃ","i":"all"},{"w":"κτίσει","i":"creation"},{"w":"τῇ","i":"-"},{"w":"ὑπὸ","i":"under"},{"w":"τὸν","i":"-"},{"w":"οὐρανόν","i":"heaven,"},{"w":"οὗ","i":"of which"},{"w":"ἐγενόμην","i":"have become"},{"w":"ἐγὼ","i":"I"},{"w":"Παῦλος","i":"Paul"},{"w":"διάκονος","i":"a minister."}],"24":[{"w":"Νῦν","i":"Now"},{"w":"χαίρω","i":"I rejoice"},{"w":"ἐν","i":"in"},{"w":"τοῖς","i":"the"},{"w":"παθήμασιν","i":"sufferings"},{"w":"ὑπὲρ","i":"for"},{"w":"ὑμῶν","i":"you,"},{"w":"καὶ","i":"and"},{"w":"ἀνταναπληρῶ","i":"I am filling up"},{"w":"τὰ","i":"that which"},{"w":"ὑστερήματα","i":"is lacking"},{"w":"τῶν","i":"of the"},{"w":"θλίψεων","i":"tribulations"},{"w":"τοῦ","i":"-"},{"w":"Χριστοῦ","i":"of Christ"},{"w":"ἐν","i":"in"},{"w":"τῇ","i":"the"},{"w":"σαρκί","i":"flesh"},{"w":"μου","i":"of me"},{"w":"ὑπὲρ","i":"for"},{"w":"τοῦ","i":"the"},{"w":"σώματος","i":"body"},{"w":"αὐτοῦ","i":"of Him"},{"w":"ὅ","i":"which"},{"w":"ἐστιν","i":"is"},{"w":"ἡ","i":"the"},{"w":"ἐκκλησία","i":"church,"}],"25":[{"w":"ἧς","i":"of which"},{"w":"ἐγενόμην","i":"became"},{"w":"ἐγὼ","i":"I"},{"w":"διάκονος","i":"a minister,"},{"w":"κατὰ","i":"according to"},{"w":"τὴν","i":"the"},{"w":"οἰκονομίαν","i":"administration"},{"w":"τοῦ","i":"-"},{"w":"Θεοῦ","i":"of God"},{"w":"τὴν","i":"-"},{"w":"δοθεῖσάν","i":"having been given"},{"w":"μοι","i":"me"},{"w":"εἰς","i":"toward"},{"w":"ὑμᾶς","i":"you,"},{"w":"πληρῶσαι","i":"to complete"},{"w":"τὸν","i":"the"},{"w":"λόγον","i":"word"},{"w":"τοῦ","i":"-"},{"w":"Θεοῦ","i":"of God,"}],"26":[{"w":"τὸ","i":"the"},{"w":"μυστήριον","i":"mystery"},{"w":"τὸ","i":"-"},{"w":"ἀποκεκρυμμένον","i":"having been hidden"},{"w":"ἀπὸ","i":"from"},{"w":"τῶν","i":"the"},{"w":"αἰώνων","i":"ages"},{"w":"καὶ","i":"and"},{"w":"ἀπὸ","i":"from"},{"w":"τῶν","i":"the"},{"w":"γενεῶν","i":"generations,"},{"w":"νῦν","i":"now"},{"w":"δὲ","i":"however"},{"w":"ἐφανερώθη","i":"having been manifested"},{"w":"τοῖς","i":"to the"},{"w":"ἁγίοις","i":"saints"},{"w":"αὐτοῦ","i":"of Him,"}],"27":[{"w":"οἷς","i":"to whom"},{"w":"ἠθέλησεν","i":"has willed"},{"w":"ὁ","i":"-"},{"w":"Θεὸς","i":"God"},{"w":"γνωρίσαι","i":"to make known"},{"w":"τί","i":"what [is]"},{"w":"τὸ","i":"the"},{"w":"πλοῦτος","i":"riches"},{"w":"τῆς","i":"of the"},{"w":"δόξης","i":"glory"},{"w":"τοῦ","i":"of the"},{"w":"μυστηρίου","i":"mystery"},{"w":"τούτου","i":"this"},{"w":"ἐν","i":"among"},{"w":"τοῖς","i":"the"},{"w":"ἔθνεσιν","i":"Gentiles,"},{"w":"ὅ","i":"which"},{"w":"ἐστιν","i":"is"},{"w":"Χριστὸς","i":"Christ"},{"w":"ἐν","i":"in"},{"w":"ὑμῖν","i":"you,"},{"w":"ἡ","i":"the"},{"w":"ἐλπὶς","i":"hope"},{"w":"τῆς","i":"-"},{"w":"δόξης","i":"of glory,"}],"28":[{"w":"ὃν","i":"whom"},{"w":"ἡμεῖς","i":"we"},{"w":"καταγγέλλομεν","i":"preach,"},{"w":"νουθετοῦντες","i":"admonishing"},{"w":"πάντα","i":"every"},{"w":"ἄνθρωπον","i":"man"},{"w":"καὶ","i":"and"},{"w":"διδάσκοντες","i":"teaching"},{"w":"πάντα","i":"every"},{"w":"ἄνθρωπον","i":"man"},{"w":"ἐν","i":"in"},{"w":"πάσῃ","i":"all"},{"w":"σοφίᾳ","i":"wisdom,"},{"w":"ἵνα","i":"so that"},{"w":"παραστήσωμεν","i":"we may present"},{"w":"πάντα","i":"every"},{"w":"ἄνθρωπον","i":"man"},{"w":"τέλειον","i":"perfect"},{"w":"ἐν","i":"in"},{"w":"Χριστῷ","i":"Christ."}],"29":[{"w":"Εἰς","i":"Unto"},{"w":"ὃ","i":"this"},{"w":"καὶ","i":"also"},{"w":"κοπιῶ","i":"I toil,"},{"w":"ἀγωνιζόμενος","i":"striving"},{"w":"κατὰ","i":"according to"},{"w":"τὴν","i":"the"},{"w":"ἐνέργειαν","i":"energy"},{"w":"αὐτοῦ","i":"of Him"},{"w":"τὴν","i":"-"},{"w":"ἐνεργουμένην","i":"working"},{"w":"ἐν","i":"in"},{"w":"ἐμοὶ","i":"me"},{"w":"ἐν","i":"in"},{"w":"δυνάμει","i":"power."}]},"2":{"1":[{"w":"Θέλω","i":"I want"},{"w":"γὰρ","i":"for"},{"w":"ὑμᾶς","i":"you"},{"w":"εἰδέναι","i":"to know"},{"w":"ἡλίκον","i":"how great"},{"w":"ἀγῶνα","i":"a struggle"},{"w":"ἔχω","i":"I am having"},{"w":"ὑπὲρ","i":"for"},{"w":"ὑμῶν","i":"you,"},{"w":"καὶ","i":"and"},{"w":"τῶν","i":"those"},{"w":"ἐν","i":"in"},{"w":"Λαοδικείᾳ","i":"Laodicea,"},{"w":"καὶ","i":"and"},{"w":"ὅσοι","i":"as many as"},{"w":"οὐχ","i":"not"},{"w":"ἑόρακαν","i":"have seen"},{"w":"τὸ","i":"the"},{"w":"πρόσωπόν","i":"face"},{"w":"μου","i":"of me"},{"w":"ἐν","i":"in"},{"w":"σαρκί","i":"[the] flesh,"}],"2":[{"w":"ἵνα","i":"that"},{"w":"παρακληθῶσιν","i":"may be encouraged"},{"w":"αἱ","i":"the"},{"w":"καρδίαι","i":"hearts"},{"w":"αὐτῶν","i":"of them,"},{"w":"συμβιβασθέντες","i":"having been knit together"},{"w":"ἐν","i":"in"},{"w":"ἀγάπῃ","i":"love,"},{"w":"καὶ","i":"and"},{"w":"εἰς","i":"to"},{"w":"πᾶν","i":"all"},{"w":"πλοῦτος","i":"[the] riches"},{"w":"τῆς","i":"of the"},{"w":"πληροφορίας","i":"full assurance"},{"w":"τῆς","i":"-"},{"w":"συνέσεως","i":"of understanding,"},{"w":"εἰς","i":"to"},{"w":"ἐπίγνωσιν","i":"[the] knowledge"},{"w":"τοῦ","i":"of the"},{"w":"μυστηρίου","i":"mystery"},{"w":"τοῦ","i":"-"},{"w":"Θεοῦ","i":"of God,"},{"w":"Χριστοῦ","i":"[which is] Christ,"}],"3":[{"w":"ἐν","i":"in"},{"w":"ᾧ","i":"whom"},{"w":"εἰσιν","i":"are"},{"w":"πάντες","i":"all"},{"w":"οἱ","i":"the"},{"w":"θησαυροὶ","i":"treasures"},{"w":"τῆς","i":"-"},{"w":"σοφίας","i":"of wisdom"},{"w":"καὶ","i":"and"},{"w":"γνώσεως","i":"of knowledge"},{"w":"ἀπόκρυφοι","i":"hidden."}],"4":[{"w":"Τοῦτο","i":"This"},{"w":"λέγω","i":"I say"},{"w":"ἵνα","i":"so that"},{"w":"μηδεὶς","i":"no one"},{"w":"ὑμᾶς","i":"you"},{"w":"παραλογίζηται","i":"might delude"},{"w":"ἐν","i":"by"},{"w":"πιθανολογίᾳ","i":"persuasive speech."}],"5":[{"w":"εἰ","i":"If"},{"w":"γὰρ","i":"truly"},{"w":"καὶ","i":"indeed"},{"w":"τῇ","i":"in the"},{"w":"σαρκὶ","i":"flesh"},{"w":"ἄπειμι","i":"I am absent,"},{"w":"ἀλλὰ","i":"yet"},{"w":"τῷ","i":"-"},{"w":"πνεύματι","i":"in spirit"},{"w":"σὺν","i":"with"},{"w":"ὑμῖν","i":"you"},{"w":"εἰμι","i":"I am,"},{"w":"χαίρων","i":"rejoicing"},{"w":"καὶ","i":"and"},{"w":"βλέπων","i":"seeing"},{"w":"ὑμῶν","i":"your"},{"w":"τὴν","i":"-"},{"w":"τάξιν","i":"good order"},{"w":"καὶ","i":"and"},{"w":"τὸ","i":"the"},{"w":"στερέωμα","i":"firmness"},{"w":"τῆς","i":"of the"},{"w":"εἰς","i":"in"},{"w":"Χριστὸν","i":"Christ"},{"w":"πίστεως","i":"faith"},{"w":"ὑμῶν","i":"of you."}],"6":[{"w":"Ὡς","i":"Just as"},{"w":"οὖν","i":"therefore"},{"w":"παρελάβετε","i":"you have received"},{"w":"τὸν","i":"-"},{"w":"Χριστὸν","i":"Christ"},{"w":"Ἰησοῦν","i":"Jesus"},{"w":"τὸν","i":"the"},{"w":"Κύριον","i":"Lord,"},{"w":"ἐν","i":"in"},{"w":"αὐτῷ","i":"Him"},{"w":"περιπατεῖτε","i":"walk,"}],"7":[{"w":"ἐρριζωμένοι","i":"having been rooted"},{"w":"καὶ","i":"and"},{"w":"ἐποικοδομούμενοι","i":"being built up"},{"w":"ἐν","i":"in"},{"w":"αὐτῷ","i":"Him,"},{"w":"καὶ","i":"and"},{"w":"βεβαιούμενοι","i":"being strengthened in"},{"w":"τῇ","i":"the"},{"w":"πίστει","i":"faith"},{"w":"καθὼς","i":"just as"},{"w":"ἐδιδάχθητε","i":"you were taught,"},{"w":"περισσεύοντες","i":"abounding"},{"w":"ἐν","i":"with"},{"w":"εὐχαριστίᾳ","i":"thanksgiving."}],"8":[{"w":"Βλέπετε","i":"Take heed"},{"w":"μή","i":"lest"},{"w":"τις","i":"anyone"},{"w":"ὑμᾶς","i":"you"},{"w":"ἔσται","i":"there will be"},{"w":"ὁ","i":"-"},{"w":"συλαγωγῶν","i":"taking captive"},{"w":"διὰ","i":"through"},{"w":"τῆς","i":"-"},{"w":"φιλοσοφίας","i":"philosophy"},{"w":"καὶ","i":"and"},{"w":"κενῆς","i":"empty"},{"w":"ἀπάτης","i":"deceit,"},{"w":"κατὰ","i":"according to"},{"w":"τὴν","i":"the"},{"w":"παράδοσιν","i":"tradition"},{"w":"τῶν","i":"-"},{"w":"ἀνθρώπων","i":"of men,"},{"w":"κατὰ","i":"according to"},{"w":"τὰ","i":"the"},{"w":"στοιχεῖα","i":"principles"},{"w":"τοῦ","i":"of the"},{"w":"κόσμου","i":"world"},{"w":"καὶ","i":"and"},{"w":"οὐ","i":"not"},{"w":"κατὰ","i":"according to"},{"w":"Χριστόν","i":"Christ."}],"9":[{"w":"ὅτι","i":"For"},{"w":"ἐν","i":"in"},{"w":"αὐτῷ","i":"Him"},{"w":"κατοικεῖ","i":"dwells"},{"w":"πᾶν","i":"all"},{"w":"τὸ","i":"the"},{"w":"πλήρωμα","i":"fullness"},{"w":"τῆς","i":"of the"},{"w":"Θεότητος","i":"Deity"},{"w":"σωματικῶς","i":"bodily;"}],"10":[{"w":"καὶ","i":"and"},{"w":"ἐστὲ","i":"you are"},{"w":"ἐν","i":"in"},{"w":"αὐτῷ","i":"Him"},{"w":"πεπληρωμένοι","i":"complete,"},{"w":"ὅς","i":"who"},{"w":"ἐστιν","i":"is"},{"w":"ἡ","i":"the"},{"w":"κεφαλὴ","i":"head"},{"w":"πάσης","i":"of all"},{"w":"ἀρχῆς","i":"rule"},{"w":"καὶ","i":"and"},{"w":"ἐξουσίας","i":"authority,"}],"11":[{"w":"ἐν","i":"in"},{"w":"ᾧ","i":"whom"},{"w":"καὶ","i":"also"},{"w":"περιετμήθητε","i":"you were circumcised"},{"w":"περιτομῇ","i":"with [the] circumcision"},{"w":"ἀχειροποιήτῳ","i":"made without hands,"},{"w":"ἐν","i":"in"},{"w":"τῇ","i":"the"},{"w":"ἀπεκδύσει","i":"removal"},{"w":"τοῦ","i":"of the"},{"w":"σώματος","i":"body"},{"w":"τῆς","i":"of the"},{"w":"σαρκός","i":"flesh,"},{"w":"ἐν","i":"in"},{"w":"τῇ","i":"the"},{"w":"περιτομῇ","i":"circumcision"},{"w":"τοῦ","i":"-"},{"w":"Χριστοῦ","i":"of Christ,"}],"12":[{"w":"συνταφέντες","i":"having been buried with"},{"w":"αὐτῷ","i":"Him"},{"w":"ἐν","i":"in"},{"w":"τῷ","i":"-"},{"w":"βαπτισμῷ","i":"baptism,"},{"w":"ἐν","i":"in"},{"w":"ᾧ","i":"which"},{"w":"καὶ","i":"also"},{"w":"συνηγέρθητε","i":"you were raised with [Him]"},{"w":"διὰ","i":"through"},{"w":"τῆς","i":"the"},{"w":"πίστεως","i":"faith"},{"w":"τῆς","i":"of the"},{"w":"ἐνεργείας","i":"working"},{"w":"τοῦ","i":"-"},{"w":"Θεοῦ","i":"of God,"},{"w":"τοῦ","i":"the [One]"},{"w":"ἐγείραντος","i":"having raised"},{"w":"αὐτὸν","i":"Him"},{"w":"ἐκ","i":"out from"},{"w":"νεκρῶν","i":"the dead."}],"13":[{"w":"Καὶ","i":"And"},{"w":"ὑμᾶς","i":"you"},{"w":"νεκροὺς","i":"dead"},{"w":"ὄντας","i":"being"},{"w":"ἐν","i":"in"},{"w":"τοῖς","i":"the"},{"w":"παραπτώμασιν","i":"trespasses"},{"w":"καὶ","i":"and"},{"w":"τῇ","i":"in the"},{"w":"ἀκροβυστίᾳ","i":"uncircumcision"},{"w":"τῆς","i":"of the"},{"w":"σαρκὸς","i":"flesh"},{"w":"ὑμῶν","i":"of you,"},{"w":"συνεζωοποίησεν","i":"He made alive together"},{"w":"ὑμᾶς","i":"you"},{"w":"σὺν","i":"with"},{"w":"αὐτῷ","i":"Him,"},{"w":"χαρισάμενος","i":"having forgiven"},{"w":"ἡμῖν","i":"us"},{"w":"πάντα","i":"all"},{"w":"τὰ","i":"the"},{"w":"παραπτώματα","i":"transgressions,"}],"14":[{"w":"ἐξαλείψας","i":"having blotted out"},{"w":"τὸ","i":"the"},{"w":"καθ᾽","i":"against"},{"w":"ἡμῶν","i":"us"},{"w":"χειρόγραφον","i":"handwriting"},{"w":"τοῖς","i":"in the"},{"w":"δόγμασιν","i":"decrees,"},{"w":"ὃ","i":"which"},{"w":"ἦν","i":"was"},{"w":"ὑπεναντίον","i":"adverse"},{"w":"ἡμῖν","i":"to us;"},{"w":"καὶ","i":"and"},{"w":"αὐτὸ","i":"it"},{"w":"ἦρκεν","i":"He has taken"},{"w":"ἐκ","i":"out of"},{"w":"τοῦ","i":"the"},{"w":"μέσου","i":"way,"},{"w":"προσηλώσας","i":"having nailed"},{"w":"αὐτὸ","i":"it"},{"w":"τῷ","i":"to the"},{"w":"σταυρῷ","i":"cross."}],"15":[{"w":"ἀπεκδυσάμενος","i":"Having disarmed"},{"w":"τὰς","i":"the"},{"w":"ἀρχὰς","i":"rulers"},{"w":"καὶ","i":"and"},{"w":"τὰς","i":"the"},{"w":"ἐξουσίας","i":"authorities,"},{"w":"ἐδειγμάτισεν","i":"He made a show [of them]"},{"w":"ἐν","i":"in"},{"w":"παρρησίᾳ","i":"public,"},{"w":"θριαμβεύσας","i":"having triumphed"},{"w":"αὐτοὺς","i":"over them"},{"w":"ἐν","i":"in"},{"w":"αὐτῷ","i":"it."}],"16":[{"w":"Μὴ","i":"Not"},{"w":"οὖν","i":"therefore"},{"w":"τις","i":"anyone"},{"w":"ὑμᾶς","i":"you"},{"w":"κρινέτω","i":"let judge"},{"w":"ἐν","i":"in regard to"},{"w":"βρώσει","i":"food,"},{"w":"καὶ","i":"or"},{"w":"ἐν","i":"in regard to"},{"w":"πόσει","i":"drink,"},{"w":"ἢ","i":"or"},{"w":"ἐν","i":"in"},{"w":"μέρει","i":"regard"},{"w":"ἑορτῆς","i":"to a feast,"},{"w":"ἢ","i":"or"},{"w":"νεομηνίας","i":"a New Moon,"},{"w":"ἢ","i":"or"},{"w":"σαββάτων","i":"Sabbaths,"}],"17":[{"w":"ἅ","i":"which"},{"w":"ἐστιν","i":"are"},{"w":"σκιὰ","i":"a shadow"},{"w":"τῶν","i":"the things"},{"w":"μελλόντων","i":"coming;"},{"w":"τὸ","i":"the"},{"w":"δὲ","i":"however"},{"w":"σῶμα","i":"body [is]"},{"w":"τοῦ","i":"-"},{"w":"Χριστοῦ","i":"of Christ."}],"18":[{"w":"μηδεὶς","i":"No one"},{"w":"ὑμᾶς","i":"you"},{"w":"καταβραβευέτω","i":"let disqualify,"},{"w":"θέλων","i":"delighting"},{"w":"ἐν","i":"in"},{"w":"ταπεινοφροσύνῃ","i":"humility"},{"w":"καὶ","i":"and"},{"w":"θρησκείᾳ","i":"[the] worship"},{"w":"τῶν","i":"of the"},{"w":"ἀγγέλων","i":"angels,"},{"w":"ἃ","i":"which"},{"w":"ἑόρακεν","i":"he has seen"},{"w":"ἐμβατεύων","i":"detailing,"},{"w":"εἰκῇ","i":"vainly"},{"w":"φυσιούμενος","i":"being puffed up"},{"w":"ὑπὸ","i":"by"},{"w":"τοῦ","i":"the"},{"w":"νοὸς","i":"mind"},{"w":"τῆς","i":"of the"},{"w":"σαρκὸς","i":"flesh"},{"w":"αὐτοῦ","i":"of him,"}],"19":[{"w":"καὶ","i":"and"},{"w":"οὐ","i":"not"},{"w":"κρατῶν","i":"holding fast"},{"w":"τὴν","i":"to the"},{"w":"Κεφαλήν","i":"head,"},{"w":"ἐξ","i":"from"},{"w":"οὗ","i":"whom"},{"w":"πᾶν","i":"all"},{"w":"τὸ","i":"the"},{"w":"σῶμα","i":"body,"},{"w":"διὰ","i":"by"},{"w":"τῶν","i":"the"},{"w":"ἁφῶν","i":"joints"},{"w":"καὶ","i":"and"},{"w":"συνδέσμων","i":"ligaments"},{"w":"ἐπιχορηγούμενον","i":"being supplied"},{"w":"καὶ","i":"and"},{"w":"συμβιβαζόμενον","i":"being knit together,"},{"w":"αὔξει","i":"increases"},{"w":"τὴν","i":"with the"},{"w":"αὔξησιν","i":"increase"},{"w":"τοῦ","i":"-"},{"w":"Θεοῦ","i":"of God."}],"20":[{"w":"Εἰ","i":"If"},{"w":"ἀπεθάνετε","i":"you have died"},{"w":"σὺν","i":"with"},{"w":"Χριστῷ","i":"Christ"},{"w":"ἀπὸ","i":"away from"},{"w":"τῶν","i":"the"},{"w":"στοιχείων","i":"principles"},{"w":"τοῦ","i":"of the"},{"w":"κόσμου","i":"world,"},{"w":"τί","i":"why"},{"w":"ὡς","i":"as if"},{"w":"ζῶντες","i":"living"},{"w":"ἐν","i":"in"},{"w":"κόσμῳ","i":"[the] world,"},{"w":"δογματίζεσθε","i":"do you submit to decrees:"}],"21":[{"w":"Μὴ","i":"Not"},{"w":"ἅψῃ","i":"you should handle!"},{"w":"μηδὲ","i":"Not"},{"w":"γεύσῃ","i":"you should taste!"},{"w":"μηδὲ","i":"Not"},{"w":"θίγῃς","i":"you should touch!"}],"22":[{"w":"ἅ","i":"which"},{"w":"ἐστιν","i":"are"},{"w":"πάντα","i":"all"},{"w":"εἰς","i":"unto"},{"w":"φθορὰν","i":"decay"},{"w":"τῇ","i":"with the"},{"w":"ἀποχρήσει","i":"use,"},{"w":"κατὰ","i":"according to"},{"w":"τὰ","i":"the"},{"w":"ἐντάλματα","i":"commandments"},{"w":"καὶ","i":"and"},{"w":"διδασκαλίας","i":"teachings"},{"w":"τῶν","i":"-"},{"w":"ἀνθρώπων","i":"of men,"}],"23":[{"w":"ἅτινά","i":"which"},{"w":"ἐστιν","i":"are"},{"w":"λόγον","i":"an appearance"},{"w":"μὲν","i":"indeed"},{"w":"ἔχοντα","i":"having"},{"w":"σοφίας","i":"of wisdom,"},{"w":"ἐν","i":"in"},{"w":"ἐθελοθρησκίᾳ","i":"self-imposed worship"},{"w":"καὶ","i":"and"},{"w":"ταπεινοφροσύνῃ","i":"humility"},{"w":"καὶ","i":"and"},{"w":"ἀφειδίᾳ","i":"harsh treatment"},{"w":"σώματος","i":"of [the] body,"},{"w":"οὐκ","i":"not"},{"w":"ἐν","i":"of"},{"w":"τιμῇ","i":"honor"},{"w":"τινι","i":"a certain,"},{"w":"πρὸς","i":"against"},{"w":"πλησμονὴν","i":"[the] indulgence"},{"w":"τῆς","i":"of the"},{"w":"σαρκός","i":"flesh."}]},"3":{"1":[{"w":"Εἰ","i":"If"},{"w":"οὖν","i":"then"},{"w":"συνηγέρθητε","i":"you have been raised with"},{"w":"τῷ","i":"-"},{"w":"Χριστῷ","i":"Christ,"},{"w":"τὰ","i":"the things"},{"w":"ἄνω","i":"above"},{"w":"ζητεῖτε","i":"seek,"},{"w":"οὗ","i":"where"},{"w":"ὁ","i":"-"},{"w":"Χριστός","i":"Christ"},{"w":"ἐστιν","i":"is"},{"w":"ἐν","i":"at [the]"},{"w":"δεξιᾷ","i":"right hand"},{"w":"τοῦ","i":"-"},{"w":"Θεοῦ","i":"of God"},{"w":"καθήμενος","i":"sitting."}],"2":[{"w":"τὰ","i":"The things"},{"w":"ἄνω","i":"above"},{"w":"φρονεῖτε","i":"set [your] minds on,"},{"w":"μὴ","i":"not"},{"w":"τὰ","i":"the things"},{"w":"ἐπὶ","i":"on"},{"w":"τῆς","i":"the"},{"w":"γῆς","i":"earth."}],"3":[{"w":"ἀπεθάνετε","i":"You have died"},{"w":"γάρ","i":"for,"},{"w":"καὶ","i":"and"},{"w":"ἡ","i":"the"},{"w":"ζωὴ","i":"life"},{"w":"ὑμῶν","i":"of you"},{"w":"κέκρυπται","i":"has been hidden"},{"w":"σὺν","i":"with"},{"w":"τῷ","i":"-"},{"w":"Χριστῷ","i":"Christ"},{"w":"ἐν","i":"in"},{"w":"τῷ","i":"-"},{"w":"Θεῷ","i":"God."}],"4":[{"w":"ὅταν","i":"When"},{"w":"ὁ","i":"-"},{"w":"Χριστὸς","i":"Christ"},{"w":"φανερωθῇ","i":"may be revealed,"},{"w":"ἡ","i":"the"},{"w":"ζωὴ","i":"life"},{"w":"ὑμῶν","i":"of you,"},{"w":"τότε","i":"then"},{"w":"καὶ","i":"also"},{"w":"ὑμεῖς","i":"you"},{"w":"σὺν","i":"with"},{"w":"αὐτῷ","i":"Him"},{"w":"φανερωθήσεσθε","i":"will appear"},{"w":"ἐν","i":"in"},{"w":"δόξῃ","i":"glory."}],"5":[{"w":"Νεκρώσατε","i":"Put to death"},{"w":"οὖν","i":"therefore"},{"w":"τὰ","i":"the"},{"w":"μέλη","i":"members"},{"w":"τὰ","i":"which [are]"},{"w":"ἐπὶ","i":"upon"},{"w":"τῆς","i":"the"},{"w":"γῆς","i":"earth:"},{"w":"πορνείαν","i":"sexual immorality,"},{"w":"ἀκαθαρσίαν","i":"impurity,"},{"w":"πάθος","i":"passion,"},{"w":"ἐπιθυμίαν","i":"desire"},{"w":"κακήν","i":"evil,"},{"w":"καὶ","i":"and"},{"w":"τὴν","i":"-"},{"w":"πλεονεξίαν","i":"covetousness,"},{"w":"ἥτις","i":"which"},{"w":"ἐστὶν","i":"is"},{"w":"εἰδωλολατρία","i":"idolatry,"}],"6":[{"w":"δι᾽","i":"because of"},{"w":"ἃ","i":"which things"},{"w":"ἔρχεται","i":"is coming"},{"w":"ἡ","i":"the"},{"w":"ὀργὴ","i":"wrath"},{"w":"τοῦ","i":"-"},{"w":"Θεοῦ","i":"of God"},{"w":"ἐπὶ","i":"on"},{"w":"τοὺς","i":"the"},{"w":"υἱοὺς","i":"sons"},{"w":"τῆς","i":"of"},{"w":"ἀπειθείας","i":"disobedience,"}],"7":[{"w":"ἐν","i":"in"},{"w":"οἷς","i":"which"},{"w":"καὶ","i":"also"},{"w":"ὑμεῖς","i":"you"},{"w":"περιεπατήσατέ","i":"walked"},{"w":"ποτε","i":"once"},{"w":"ὅτε","i":"when"},{"w":"ἐζῆτε","i":"you were living"},{"w":"ἐν","i":"in"},{"w":"τούτοις","i":"them."}],"8":[{"w":"νυνὶ","i":"Now"},{"w":"δὲ","i":"however,"},{"w":"ἀπόθεσθε","i":"put off"},{"w":"καὶ","i":"also"},{"w":"ὑμεῖς","i":"you"},{"w":"τὰ","i":"-"},{"w":"πάντα","i":"all [these] things:"},{"w":"ὀργήν","i":"anger,"},{"w":"θυμόν","i":"rage,"},{"w":"κακίαν","i":"malice,"},{"w":"βλασφημίαν","i":"slander,"},{"w":"αἰσχρολογίαν","i":"foul language"},{"w":"ἐκ","i":"out of"},{"w":"τοῦ","i":"the"},{"w":"στόματος","i":"mouth"},{"w":"ὑμῶν","i":"of you."}],"9":[{"w":"Μὴ","i":"Not"},{"w":"ψεύδεσθε","i":"do lie"},{"w":"εἰς","i":"to"},{"w":"ἀλλήλους","i":"one another,"},{"w":"ἀπεκδυσάμενοι","i":"having put off"},{"w":"τὸν","i":"the"},{"w":"παλαιὸν","i":"old"},{"w":"ἄνθρωπον","i":"man"},{"w":"σὺν","i":"with"},{"w":"ταῖς","i":"the"},{"w":"πράξεσιν","i":"practices"},{"w":"αὐτοῦ","i":"of him,"}],"10":[{"w":"καὶ","i":"and"},{"w":"ἐνδυσάμενοι","i":"having put on"},{"w":"τὸν","i":"the"},{"w":"νέον","i":"new,"},{"w":"τὸν","i":"the [one]"},{"w":"ἀνακαινούμενον","i":"being renewed"},{"w":"εἰς","i":"in"},{"w":"ἐπίγνωσιν","i":"knowledge"},{"w":"κατ᾽","i":"according to"},{"w":"εἰκόνα","i":"[the] image"},{"w":"τοῦ","i":"of the [one]"},{"w":"κτίσαντος","i":"having created"},{"w":"αὐτόν","i":"him,"}],"11":[{"w":"ὅπου","i":"where"},{"w":"οὐκ","i":"not"},{"w":"ἔνι","i":"there is"},{"w":"Ἕλλην","i":"Greek"},{"w":"καὶ","i":"and"},{"w":"Ἰουδαῖος","i":"Jew,"},{"w":"περιτομὴ","i":"circumcision"},{"w":"καὶ","i":"and"},{"w":"ἀκροβυστία","i":"uncircumcision,"},{"w":"βάρβαρος","i":"Barbarian,"},{"w":"Σκύθης","i":"Scythian,"},{"w":"δοῦλος","i":"slave,"},{"w":"ἐλεύθερος","i":"free;"},{"w":"ἀλλὰ","i":"but"},{"w":"τὰ","i":"-"},{"w":"πάντα","i":"all"},{"w":"καὶ","i":"and"},{"w":"ἐν","i":"in"},{"w":"πᾶσιν","i":"all"},{"w":"Χριστός","i":"Christ [is]."}],"12":[{"w":"Ἐνδύσασθε","i":"Put on"},{"w":"οὖν","i":"therefore,"},{"w":"ὡς","i":"as"},{"w":"ἐκλεκτοὶ","i":"[the] elect"},{"w":"τοῦ","i":"-"},{"w":"Θεοῦ","i":"of God,"},{"w":"ἅγιοι","i":"holy"},{"w":"καὶ","i":"and"},{"w":"ἠγαπημένοι","i":"beloved,"},{"w":"σπλάγχνα","i":"hearts"},{"w":"οἰκτιρμοῦ","i":"of compassion,"},{"w":"χρηστότητα","i":"kindness,"},{"w":"ταπεινοφροσύνην","i":"humility,"},{"w":"πραΰτητα","i":"gentleness,"},{"w":"μακροθυμίαν","i":"[and] patience;"}],"13":[{"w":"ἀνεχόμενοι","i":"bearing with"},{"w":"ἀλλήλων","i":"each other"},{"w":"καὶ","i":"and"},{"w":"χαριζόμενοι","i":"forgiving"},{"w":"ἑαυτοῖς","i":"each other."},{"w":"ἐάν","i":"If"},{"w":"τις","i":"anyone"},{"w":"πρός","i":"against"},{"w":"τινα","i":"another"},{"w":"ἔχῃ","i":"should have"},{"w":"μομφήν","i":"a complaint,"},{"w":"καθὼς","i":"even as"},{"w":"καὶ","i":"also"},{"w":"ὁ","i":"the"},{"w":"Κύριος","i":"Lord"},{"w":"ἐχαρίσατο","i":"has forgiven"},{"w":"ὑμῖν","i":"you,"},{"w":"οὕτως","i":"so"},{"w":"καὶ","i":"also"},{"w":"ὑμεῖς","i":"you."}],"14":[{"w":"ἐπὶ","i":"Beyond"},{"w":"πᾶσιν","i":"all"},{"w":"δὲ","i":"now"},{"w":"τούτοις","i":"these,"},{"w":"τὴν","i":"[put on] the"},{"w":"ἀγάπην","i":"love,"},{"w":"ὅ","i":"which"},{"w":"ἐστιν","i":"is"},{"w":"σύνδεσμος","i":"[the] bond"},{"w":"τῆς","i":"-"},{"w":"τελειότητος","i":"of perfect unity."}],"15":[{"w":"καὶ","i":"And"},{"w":"ἡ","i":"the"},{"w":"εἰρήνη","i":"peace"},{"w":"τοῦ","i":"-"},{"w":"Χριστοῦ","i":"from Christ"},{"w":"βραβευέτω","i":"let rule"},{"w":"ἐν","i":"in"},{"w":"ταῖς","i":"the"},{"w":"καρδίαις","i":"hearts"},{"w":"ὑμῶν","i":"of you,"},{"w":"εἰς","i":"to"},{"w":"ἣν","i":"which"},{"w":"καὶ","i":"also"},{"w":"ἐκλήθητε","i":"you were called"},{"w":"ἐν","i":"in"},{"w":"ἑνὶ","i":"one"},{"w":"σώματι","i":"body."},{"w":"καὶ","i":"And"},{"w":"εὐχάριστοι","i":"thankful"},{"w":"γίνεσθε","i":"be."}],"16":[{"w":"Ὁ","i":"The"},{"w":"λόγος","i":"word"},{"w":"τοῦ","i":"-"},{"w":"Χριστοῦ","i":"of Christ"},{"w":"ἐνοικείτω","i":"let dwell"},{"w":"ἐν","i":"in"},{"w":"ὑμῖν","i":"you"},{"w":"πλουσίως","i":"richly,"},{"w":"ἐν","i":"in"},{"w":"πάσῃ","i":"all"},{"w":"σοφίᾳ","i":"wisdom"},{"w":"διδάσκοντες","i":"teaching"},{"w":"καὶ","i":"and"},{"w":"νουθετοῦντες","i":"admonishing"},{"w":"ἑαυτοὺς","i":"each other"},{"w":"ψαλμοῖς","i":"in psalms,"},{"w":"ὕμνοις","i":"hymns,"},{"w":"ᾠδαῖς","i":"[and] songs"},{"w":"πνευματικαῖς","i":"spiritual,"},{"w":"ἐν","i":"with"},{"w":"τῇ","i":"-"},{"w":"χάριτι","i":"grace"},{"w":"ᾄδοντες","i":"singing,"},{"w":"ἐν","i":"in"},{"w":"ταῖς","i":"the"},{"w":"καρδίαις","i":"hearts"},{"w":"ὑμῶν","i":"of you,"},{"w":"τῷ","i":"to"},{"w":"Θεῷ","i":"God."}],"17":[{"w":"καὶ","i":"And"},{"w":"πᾶν","i":"everything,"},{"w":"ὅ","i":"which"},{"w":"τι","i":"what"},{"w":"ἐὰν","i":"if"},{"w":"ποιῆτε","i":"you might do"},{"w":"ἐν","i":"in"},{"w":"λόγῳ","i":"word"},{"w":"ἢ","i":"or"},{"w":"ἐν","i":"in"},{"w":"ἔργῳ","i":"deed,"},{"w":"πάντα","i":"all"},{"w":"ἐν","i":"in"},{"w":"ὀνόματι","i":"[the] name"},{"w":"Κυρίου","i":"of [the] Lord"},{"w":"Ἰησοῦ","i":"Jesus,"},{"w":"εὐχαριστοῦντες","i":"giving thanks"},{"w":"τῷ","i":"-"},{"w":"Θεῷ","i":"to God"},{"w":"Πατρὶ","i":"[the] Father"},{"w":"δι᾽","i":"through"},{"w":"αὐτοῦ","i":"Him."}],"18":[{"w":"Αἱ","i":"-"},{"w":"γυναῖκες","i":"Wives,"},{"w":"ὑποτάσσεσθε","i":"submit yourselves"},{"w":"τοῖς","i":"to the"},{"w":"ἀνδράσιν","i":"husbands,"},{"w":"ὡς","i":"as"},{"w":"ἀνῆκεν","i":"is fitting"},{"w":"ἐν","i":"in"},{"w":"Κυρίῳ","i":"[the] Lord."}],"19":[{"w":"Οἱ","i":"-"},{"w":"ἄνδρες","i":"Husbands,"},{"w":"ἀγαπᾶτε","i":"love"},{"w":"τὰς","i":"the"},{"w":"γυναῖκας","i":"wives,"},{"w":"καὶ","i":"and"},{"w":"μὴ","i":"not"},{"w":"πικραίνεσθε","i":"be harsh"},{"w":"πρὸς","i":"toward"},{"w":"αὐτάς","i":"them."}],"20":[{"w":"Τὰ","i":"-"},{"w":"τέκνα","i":"Children,"},{"w":"ὑπακούετε","i":"obey"},{"w":"τοῖς","i":"the"},{"w":"γονεῦσιν","i":"parents"},{"w":"κατὰ","i":"in"},{"w":"πάντα","i":"all things;"},{"w":"τοῦτο","i":"this"},{"w":"γὰρ","i":"for"},{"w":"εὐάρεστόν","i":"pleasing"},{"w":"ἐστιν","i":"is"},{"w":"ἐν","i":"in"},{"w":"Κυρίῳ","i":"[the] Lord."}],"21":[{"w":"Οἱ","i":"-"},{"w":"πατέρες","i":"Fathers,"},{"w":"μὴ","i":"not"},{"w":"ἐρεθίζετε","i":"do provoke"},{"w":"τὰ","i":"the"},{"w":"τέκνα","i":"children"},{"w":"ὑμῶν","i":"of you,"},{"w":"ἵνα","i":"that"},{"w":"μὴ","i":"not"},{"w":"ἀθυμῶσιν","i":"they might become discouraged."}],"22":[{"w":"Οἱ","i":"-"},{"w":"δοῦλοι","i":"Slaves,"},{"w":"ὑπακούετε","i":"obey"},{"w":"κατὰ","i":"in"},{"w":"πάντα","i":"all things"},{"w":"τοῖς","i":"the"},{"w":"κατὰ","i":"according to"},{"w":"σάρκα","i":"flesh"},{"w":"κυρίοις","i":"masters,"},{"w":"μὴ","i":"not"},{"w":"ἐν","i":"with"},{"w":"ὀφθαλμοδουλίαις","i":"eye-services"},{"w":"ὡς","i":"as"},{"w":"ἀνθρωπάρεσκοι","i":"men-pleasers,"},{"w":"ἀλλ᾽","i":"but"},{"w":"ἐν","i":"in"},{"w":"ἁπλότητι","i":"sincerity"},{"w":"καρδίας","i":"of heart,"},{"w":"φοβούμενοι","i":"fearing"},{"w":"τὸν","i":"the"},{"w":"Κύριον","i":"Lord."}],"23":[{"w":"Ὃ","i":"Whatever"},{"w":"ἐὰν","i":"if"},{"w":"ποιῆτε","i":"you might do,"},{"w":"ἐκ","i":"from"},{"w":"ψυχῆς","i":"[the] soul"},{"w":"ἐργάζεσθε","i":"work,"},{"w":"ὡς","i":"as"},{"w":"τῷ","i":"to the"},{"w":"Κυρίῳ","i":"Lord"},{"w":"καὶ","i":"and"},{"w":"οὐκ","i":"not"},{"w":"ἀνθρώποις","i":"to men,"}],"24":[{"w":"εἰδότες","i":"knowing"},{"w":"ὅτι","i":"that"},{"w":"ἀπὸ","i":"from"},{"w":"Κυρίου","i":"[the] Lord"},{"w":"ἀπολήμψεσθε","i":"you will receive"},{"w":"τὴν","i":"the"},{"w":"ἀνταπόδοσιν","i":"reward"},{"w":"τῆς","i":"of the"},{"w":"κληρονομίας","i":"inheritance."},{"w":"τῷ","i":"The"},{"w":"Κυρίῳ","i":"Lord"},{"w":"Χριστῷ","i":"Christ"},{"w":"δουλεύετε","i":"you serve."}],"25":[{"w":"ὁ","i":"The [one]"},{"w":"γὰρ","i":"for"},{"w":"ἀδικῶν","i":"doing wrong"},{"w":"κομίσεται","i":"will be repaid [for]"},{"w":"ὃ","i":"what"},{"w":"ἠδίκησεν","i":"he has done wrong,"},{"w":"καὶ","i":"and"},{"w":"οὐκ","i":"not"},{"w":"ἔστιν","i":"there is"},{"w":"προσωπολημψία","i":"partiality."}]},"4":{"1":[{"w":"Οἱ","i":"-"},{"w":"κύριοι","i":"Masters,"},{"w":"τὸ","i":"that which"},{"w":"δίκαιον","i":"[is] righteous"},{"w":"καὶ","i":"and"},{"w":"τὴν","i":"that which"},{"w":"ἰσότητα","i":"[is] equal,"},{"w":"τοῖς","i":"to the"},{"w":"δούλοις","i":"slaves"},{"w":"παρέχεσθε","i":"give,"},{"w":"εἰδότες","i":"knowing"},{"w":"ὅτι","i":"that"},{"w":"καὶ","i":"also"},{"w":"ὑμεῖς","i":"you"},{"w":"ἔχετε","i":"have"},{"w":"Κύριον","i":"a Master"},{"w":"ἐν","i":"in"},{"w":"οὐρανῷ","i":"heaven."}],"2":[{"w":"Τῇ","i":"-"},{"w":"προσευχῇ","i":"In prayer"},{"w":"προσκαρτερεῖτε","i":"continue steadfastly,"},{"w":"γρηγοροῦντες","i":"watching"},{"w":"ἐν","i":"in"},{"w":"αὐτῇ","i":"it"},{"w":"ἐν","i":"with"},{"w":"εὐχαριστίᾳ","i":"thanksgiving,"}],"3":[{"w":"προσευχόμενοι","i":"praying"},{"w":"ἅμα","i":"at the same time"},{"w":"καὶ","i":"also"},{"w":"περὶ","i":"for"},{"w":"ἡμῶν","i":"us,"},{"w":"ἵνα","i":"that"},{"w":"ὁ","i":"-"},{"w":"Θεὸς","i":"God"},{"w":"ἀνοίξῃ","i":"may open"},{"w":"ἡμῖν","i":"to us"},{"w":"θύραν","i":"a door"},{"w":"τοῦ","i":"for the"},{"w":"λόγου","i":"word,"},{"w":"λαλῆσαι","i":"to declare"},{"w":"τὸ","i":"the"},{"w":"μυστήριον","i":"mystery"},{"w":"τοῦ","i":"-"},{"w":"Χριστοῦ","i":"of Christ,"},{"w":"δι᾽","i":"on account of"},{"w":"ὃ","i":"which"},{"w":"καὶ","i":"also"},{"w":"δέδεμαι","i":"I have been bound,"}],"4":[{"w":"ἵνα","i":"so that"},{"w":"φανερώσω","i":"I should make clear"},{"w":"αὐτὸ","i":"it,"},{"w":"ὡς","i":"as"},{"w":"δεῖ","i":"it behooves"},{"w":"με","i":"me"},{"w":"λαλῆσαι","i":"to speak."}],"5":[{"w":"Ἐν","i":"In"},{"w":"σοφίᾳ","i":"wisdom"},{"w":"περιπατεῖτε","i":"walk"},{"w":"πρὸς","i":"toward"},{"w":"τοὺς","i":"those"},{"w":"ἔξω","i":"outside,"},{"w":"τὸν","i":"the"},{"w":"καιρὸν","i":"time"},{"w":"ἐξαγοραζόμενοι","i":"redeeming."}],"6":[{"w":"ὁ","i":"-"},{"w":"λόγος","i":"[Let the] speech"},{"w":"ὑμῶν","i":"of you"},{"w":"πάντοτε","i":"[be] always"},{"w":"ἐν","i":"in"},{"w":"χάριτι","i":"grace,"},{"w":"ἅλατι","i":"with salt"},{"w":"ἠρτυμένος","i":"having been seasoned,"},{"w":"εἰδέναι","i":"to know"},{"w":"πῶς","i":"how"},{"w":"δεῖ","i":"it behooves"},{"w":"ὑμᾶς","i":"you"},{"w":"ἑνὶ","i":"one"},{"w":"ἑκάστῳ","i":"each"},{"w":"ἀποκρίνεσθαι","i":"to answer."}],"7":[{"w":"Τὰ","i":"The things"},{"w":"κατ᾽","i":"concerning"},{"w":"ἐμὲ","i":"me"},{"w":"πάντα","i":"all"},{"w":"γνωρίσει","i":"will make known"},{"w":"ὑμῖν","i":"to you"},{"w":"Τυχικὸς","i":"Tychicus,"},{"w":"ὁ","i":"the"},{"w":"ἀγαπητὸς","i":"beloved"},{"w":"ἀδελφὸς","i":"brother"},{"w":"καὶ","i":"and"},{"w":"πιστὸς","i":"faithful"},{"w":"διάκονος","i":"servant"},{"w":"καὶ","i":"and"},{"w":"σύνδουλος","i":"fellow bond-servant"},{"w":"ἐν","i":"in"},{"w":"Κυρίῳ","i":"[the] Lord,"}],"8":[{"w":"ὃν","i":"whom"},{"w":"ἔπεμψα","i":"I sent"},{"w":"πρὸς","i":"to"},{"w":"ὑμᾶς","i":"you"},{"w":"εἰς","i":"for"},{"w":"αὐτὸ","i":"this very"},{"w":"τοῦτο","i":"purpose,"},{"w":"ἵνα","i":"that"},{"w":"γνῶτε","i":"you might know"},{"w":"τὰ","i":"the things"},{"w":"περὶ","i":"concerning"},{"w":"ἡμῶν","i":"us,"},{"w":"καὶ","i":"and"},{"w":"παρακαλέσῃ","i":"he may encourage"},{"w":"τὰς","i":"the"},{"w":"καρδίας","i":"hearts"},{"w":"ὑμῶν","i":"of you,"}],"9":[{"w":"σὺν","i":"with"},{"w":"Ὀνησίμῳ","i":"Onesimus,"},{"w":"τῷ","i":"the"},{"w":"πιστῷ","i":"faithful"},{"w":"καὶ","i":"and"},{"w":"ἀγαπητῷ","i":"beloved"},{"w":"ἀδελφῷ","i":"brother,"},{"w":"ὅς","i":"who"},{"w":"ἐστιν","i":"is"},{"w":"ἐξ","i":"[one] of"},{"w":"ὑμῶν","i":"you."},{"w":"πάντα","i":"All things"},{"w":"ὑμῖν","i":"to you"},{"w":"γνωρίσουσιν","i":"they will make known"},{"w":"τὰ","i":"-"},{"w":"ὧδε","i":"here."}],"10":[{"w":"Ἀσπάζεται","i":"Greets"},{"w":"ὑμᾶς","i":"you,"},{"w":"Ἀρίσταρχος","i":"Aristarchus"},{"w":"ὁ","i":"the"},{"w":"συναιχμάλωτός","i":"fellow prisoner"},{"w":"μου","i":"of me,"},{"w":"καὶ","i":"and"},{"w":"Μᾶρκος","i":"Mark,"},{"w":"ὁ","i":"the"},{"w":"ἀνεψιὸς","i":"cousin"},{"w":"Βαρνάβα","i":"of Barnabas,"},{"w":"περὶ","i":"concerning"},{"w":"οὗ","i":"whom"},{"w":"ἐλάβετε","i":"you have received"},{"w":"ἐντολάς","i":"instructions —"},{"w":"ἐὰν","i":"if"},{"w":"ἔλθῃ","i":"he comes"},{"w":"πρὸς","i":"to"},{"w":"ὑμᾶς","i":"you,"},{"w":"δέξασθε","i":"welcome"},{"w":"αὐτόν","i":"him —"}],"11":[{"w":"καὶ","i":"and also"},{"w":"Ἰησοῦς","i":"Jesus"},{"w":"ὁ","i":"-"},{"w":"λεγόμενος","i":"called"},{"w":"Ἰοῦστος","i":"Justus,"},{"w":"οἱ","i":"-"},{"w":"ὄντες","i":"being"},{"w":"ἐκ","i":"among"},{"w":"περιτομῆς","i":"[the] circumcision"},{"w":"οὗτοι","i":"these"},{"w":"μόνοι","i":"only"},{"w":"συνεργοὶ","i":"fellow workers"},{"w":"εἰς","i":"for"},{"w":"τὴν","i":"the"},{"w":"βασιλείαν","i":"kingdom"},{"w":"τοῦ","i":"-"},{"w":"Θεοῦ","i":"of God,"},{"w":"οἵτινες","i":"who"},{"w":"ἐγενήθησάν","i":"have been"},{"w":"μοι","i":"to me"},{"w":"παρηγορία","i":"a comfort."}],"12":[{"w":"Ἀσπάζεται","i":"Greets"},{"w":"ὑμᾶς","i":"you,"},{"w":"Ἐπαφρᾶς","i":"Epaphras"},{"w":"ὁ","i":"who [is]"},{"w":"ἐξ","i":"[one] of"},{"w":"ὑμῶν","i":"you,"},{"w":"δοῦλος","i":"a servant"},{"w":"Χριστοῦ","i":"of Christ"},{"w":"Ἰησοῦ","i":"Jesus,"},{"w":"πάντοτε","i":"always"},{"w":"ἀγωνιζόμενος","i":"struggling"},{"w":"ὑπὲρ","i":"for"},{"w":"ὑμῶν","i":"you"},{"w":"ἐν","i":"in"},{"w":"ταῖς","i":"the"},{"w":"προσευχαῖς","i":"prayers,"},{"w":"ἵνα","i":"so that"},{"w":"σταθῆτε","i":"you may stand"},{"w":"τέλειοι","i":"mature"},{"w":"καὶ","i":"and"},{"w":"πεπληροφορημένοι","i":"fully assured"},{"w":"ἐν","i":"in"},{"w":"παντὶ","i":"all"},{"w":"θελήματι","i":"[the] will"},{"w":"τοῦ","i":"-"},{"w":"Θεοῦ","i":"of God."}],"13":[{"w":"μαρτυρῶ","i":"I bear witness"},{"w":"γὰρ","i":"for"},{"w":"αὐτῷ","i":"to him"},{"w":"ὅτι","i":"that"},{"w":"ἔχει","i":"he has"},{"w":"πολὺν","i":"great"},{"w":"πόνον","i":"concern"},{"w":"ὑπὲρ","i":"for"},{"w":"ὑμῶν","i":"you"},{"w":"καὶ","i":"and"},{"w":"τῶν","i":"those"},{"w":"ἐν","i":"in"},{"w":"Λαοδικείᾳ","i":"Laodicea"},{"w":"καὶ","i":"and"},{"w":"τῶν","i":"them"},{"w":"ἐν","i":"in"},{"w":"Ἱεραπόλει","i":"Hiera polis."}],"14":[{"w":"Ἀσπάζεται","i":"Greets"},{"w":"ὑμᾶς","i":"you,"},{"w":"Λουκᾶς","i":"Luke"},{"w":"ὁ","i":"the"},{"w":"ἰατρὸς","i":"physician"},{"w":"ὁ","i":"-"},{"w":"ἀγαπητὸς","i":"beloved,"},{"w":"καὶ","i":"and also"},{"w":"Δημᾶς","i":"Demas."}],"15":[{"w":"Ἀσπάσασθε","i":"Greet"},{"w":"τοὺς","i":"the"},{"w":"ἐν","i":"in"},{"w":"Λαοδικείᾳ","i":"Laodicea"},{"w":"ἀδελφοὺς","i":"brothers,"},{"w":"καὶ","i":"and also"},{"w":"Νύμφαν","i":"Nympha,"},{"w":"καὶ","i":"and"},{"w":"τὴν","i":"the"},{"w":"κατ᾽","i":"in"},{"w":"οἶκον","i":"house"},{"w":"αὐτῆς","i":"of her"},{"w":"ἐκκλησίαν","i":"church."}],"16":[{"w":"Καὶ","i":"And"},{"w":"ὅταν","i":"when"},{"w":"ἀναγνωσθῇ","i":"shall be read"},{"w":"παρ᾽","i":"among"},{"w":"ὑμῖν","i":"you"},{"w":"ἡ","i":"the"},{"w":"ἐπιστολή","i":"letter,"},{"w":"ποιήσατε","i":"cause"},{"w":"ἵνα","i":"that"},{"w":"καὶ","i":"also"},{"w":"ἐν","i":"in"},{"w":"τῇ","i":"the"},{"w":"Λαοδικέων","i":"of [the] Laodiceans"},{"w":"ἐκκλησίᾳ","i":"church"},{"w":"ἀναγνωσθῇ","i":"it may be read,"},{"w":"καὶ","i":"and"},{"w":"τὴν","i":"the [one]"},{"w":"ἐκ","i":"from"},{"w":"Λαοδικείας","i":"Laodicea"},{"w":"ἵνα","i":"that"},{"w":"καὶ","i":"also"},{"w":"ὑμεῖς","i":"you"},{"w":"ἀναγνῶτε","i":"may read."}],"17":[{"w":"Καὶ","i":"And"},{"w":"εἴπατε","i":"say"},{"w":"Ἀρχίππῳ","i":"to Archippus,"},{"w":"Βλέπε","i":"Take heed to"},{"w":"τὴν","i":"the"},{"w":"διακονίαν","i":"ministry"},{"w":"ἣν","i":"that"},{"w":"παρέλαβες","i":"you have received"},{"w":"ἐν","i":"in"},{"w":"Κυρίῳ","i":"[the] Lord,"},{"w":"ἵνα","i":"that"},{"w":"αὐτὴν","i":"it"},{"w":"πληροῖς","i":"you may fulfill."}],"18":[{"w":"Ὁ","i":"The"},{"w":"ἀσπασμὸς","i":"greeting"},{"w":"τῇ","i":"[is] in the"},{"w":"ἐμῇ","i":"own"},{"w":"χειρὶ","i":"hand —"},{"w":"Παύλου","i":"Paul."},{"w":"Μνημονεύετέ","i":"Remember"},{"w":"μου","i":"my"},{"w":"τῶν","i":"-"},{"w":"δεσμῶν","i":"chains."},{"w":"Ἡ","i":"-"},{"w":"χάρις","i":"Grace [be]"},{"w":"μεθ᾽","i":"with"},{"w":"ὑμῶν","i":"you."}]}}